<title>Private Partner Automation Hub Installation Guide</title>
<productname>Private Partner Automation Hub</productname>
<productnumber>2.4</productnumber>
<subtitle>Private Partner Automation Hub Installation Guide</subtitle>
<abstract>
    <para>Private Partner Automation Hub Installation Guide</para>
</abstract>
<authorgroup>
    <orgname>Red Hat Customer Content Services </orgname>
</authorgroup>
<xi:include href="Common_Content/Legal_Notice.xml" xmlns:xi="http://www.w3.org/2001/XInclude" />
